{
    "keep": {
        "days": true,
        "amount": 14
    },
    "auditLog": "C:\\Web Technology\\React_Application\\new\\Milk_App\\logs\\.ab706eb247a7980b79d1dff02ffecf2dec871418-audit.json",
    "files": [
        {
            "date": 1752116483303,
            "name": "C:\\Web Technology\\React_Application\\new\\Milk_App\\logs\\activity-2025-07-10.log",
            "hash": "bc1db49fc4e182235ffd2c62b3c56b3681a0d9933f29170e3d1f347794eab196"
        },
        {
            "date": 1752204844762,
            "name": "C:\\Web Technology\\React_Application\\new\\Milk_App\\logs\\activity-2025-07-11.log",
            "hash": "82c3a3907d28e8e208975d5a4023adaae2cb5aa0ce429ea5f8e116642c96b732"
        },
        {
            "date": 1752292867563,
            "name": "C:\\Web Technology\\React_Application\\new\\Milk_App\\logs\\activity-2025-07-12.log",
            "hash": "4bafe85fc02f1b8d6b90a4aca789d1a7b52b1a558113a91938eabf4d93ad0f05"
        },
        {
            "date": 1752345361811,
            "name": "C:\\Web Technology\\React_Application\\new\\Milk_App\\logs\\activity-2025-07-13.log",
            "hash": "39b9f65520b7c1b3222d7a0724b5b1d8802b3ddbe26802d245db7adb8b503e13"
        },
        {
            "date": 1752585434811,
            "name": "C:\\Web Technology\\React_Application\\new\\Milk_App\\logs\\activity-2025-07-15.log",
            "hash": "9259d9b3d837abbd0563cb22659c3ff76bb8bd0f3b6500491f4215d4053f0c38"
        },
        {
            "date": 1752953972896,
            "name": "C:\\Web Technology\\React_Application\\new\\Milk_App\\logs\\activity-2025-07-20.log",
            "hash": "5c16a51aed5d2d097ca23a6095a5e2b89afaa6117758d1ad83736b00b237c000"
        },
        {
            "date": 1753036218983,
            "name": "C:\\Web Technology\\React_Application\\new\\Milk_App\\logs\\activity-2025-07-21.log",
            "hash": "5d98d98eec6c102db9702ad302c49844dca1ccea9fd31766d35f31a2a7691db2"
        },
        {
            "date": 1753199172590,
            "name": "C:\\Web Technology\\React_Application\\new\\Milk_App\\logs\\activity-2025-07-22.log",
            "hash": "9376c0af20a221b18ef80963e4c8a23e679b7534d26acffe5c8c5f65748b23a3"
        },
        {
            "date": 1753209144016,
            "name": "C:\\Web Technology\\React_Application\\new\\Milk_App\\logs\\activity-2025-07-23.log",
            "hash": "79235a96a5af2b1776a52cfc3d01b6b2166985edade135792670db0adb29057c"
        },
        {
            "date": 1753295628096,
            "name": "C:\\Web Technology\\React_Application\\new\\Milk_App\\logs\\activity-2025-07-24.log",
            "hash": "dde42e91755291e128fe28853e00db95ef9836a3fd208ba6a6dd7103f816bc9d"
        }
    ],
    "hashType": "sha256"
}